README.rst
setup.py
gitsome/__init__.py
gitsome/compat.py
gitsome/completer.py
gitsome/completions.py
gitsome/completions_git.py
gitsome/config.py
gitsome/formatter.py
gitsome/github.py
gitsome/githubcli.py
gitsome/main.py
gitsome/main_cli.py
gitsome/parser_table.py
gitsome/rss_feed.py
gitsome/table.py
gitsome/utils.py
gitsome/view_entry.py
gitsome/web_viewer.py
gitsome.egg-info/PKG-INFO
gitsome.egg-info/SOURCES.txt
gitsome.egg-info/dependency_links.txt
gitsome.egg-info/entry_points.txt
gitsome.egg-info/requires.txt
gitsome.egg-info/top_level.txt
gitsome/lib/__init__.py
gitsome/lib/debug_timer.py
gitsome/lib/pretty_date_time.py
gitsome/lib/github3/__about__.py
gitsome/lib/github3/__init__.py
gitsome/lib/github3/api.py
gitsome/lib/github3/auths.py
gitsome/lib/github3/decorators.py
gitsome/lib/github3/events.py
gitsome/lib/github3/exceptions.py
gitsome/lib/github3/git.py
gitsome/lib/github3/github.py
gitsome/lib/github3/licenses.py
gitsome/lib/github3/models.py
gitsome/lib/github3/notifications.py
gitsome/lib/github3/null.py
gitsome/lib/github3/orgs.py
gitsome/lib/github3/pulls.py
gitsome/lib/github3/session.py
gitsome/lib/github3/structs.py
gitsome/lib/github3/users.py
gitsome/lib/github3/utils.py
gitsome/lib/github3/gists/__init__.py
gitsome/lib/github3/gists/comment.py
gitsome/lib/github3/gists/file.py
gitsome/lib/github3/gists/gist.py
gitsome/lib/github3/gists/history.py
gitsome/lib/github3/issues/__init__.py
gitsome/lib/github3/issues/comment.py
gitsome/lib/github3/issues/event.py
gitsome/lib/github3/issues/issue.py
gitsome/lib/github3/issues/label.py
gitsome/lib/github3/issues/milestone.py
gitsome/lib/github3/repos/__init__.py
gitsome/lib/github3/repos/branch.py
gitsome/lib/github3/repos/comment.py
gitsome/lib/github3/repos/commit.py
gitsome/lib/github3/repos/comparison.py
gitsome/lib/github3/repos/contents.py
gitsome/lib/github3/repos/deployment.py
gitsome/lib/github3/repos/hook.py
gitsome/lib/github3/repos/issue_import.py
gitsome/lib/github3/repos/pages.py
gitsome/lib/github3/repos/release.py
gitsome/lib/github3/repos/repo.py
gitsome/lib/github3/repos/stats.py
gitsome/lib/github3/repos/status.py
gitsome/lib/github3/repos/tag.py
