Metadata-Version: 1.1
Name: gitsome
Version: 0.6.0
Summary: A Supercharged Git/Shell Autocompleter with GitHub Integration.
Home-page: https://github.com/donnemartin/gitsome
Author: Donne Martin
Author-email: donne.martin@gmail.com
License: Apache License 2.0
Platform: Cross Platform
Classifier: Intended Audience :: Developers
Classifier: Intended Audience :: System Administrators
Classifier: License :: OSI Approved :: Apache Software License
Classifier: Natural Language :: English
Classifier: Programming Language :: Python :: 3
Classifier: Programming Language :: Python :: 3.4
Classifier: Programming Language :: Python :: 3.5
Classifier: Topic :: Software Development
Classifier: Topic :: Software Development :: Libraries :: Python Modules
